{
    "basic_info": {
      "name": "Lino Moreau",
      "titles": [ "BTS SIO SLAM", "Développeur Informatique"],
      "social": [
        {
          "name": "github",
          "url": "https://github.com",
          "class": "fab fa-github"
        },
        {
          "name": "instagram",
          "url": "https://www.instagram.com",
          "class": "fab fa-instagram"
        }
      ],
      "image": "avatar.png"
    },
    "skills": {
      "icons": [
        {
          "name": "HTML 5",
          "class": "devicon-html5-plain",
          "level": "95"
        },
        {
          "name": "CSS 3",
          "class": "devicon-css3-plain",
          "level": "95"
        },
        {
          "name": "Symfony",
          "class": "devicon-symfony-original",
          "level": "80"
        },
        {
          "name": "PHP",
          "class": "devicon-php-plain",
          "level": "90"
        },
        {
          "name": "JavaScript",
          "class": "devicon-javascript-plain",
          "level": "70"
        },
        {
          "name": "Java",
          "class": "devicon-java-plain",
          "level": "75"
        },
        {
          "name": "Android",
          "class": "devicon-android-plain",
          "level": "85"
        },
        {
          "name": "Python",
          "class": "devicon-python-plain",
          "level": "65"
        },
        {
          "name": "MySql",
          "class": "devicon-mysql-plain",
          "level": "60"
        }
      ]
    }
  }